adlib/__init__.py
adlib/adversaries/__init__.py
adlib/adversaries/adversarial_learning.py
adlib/adversaries/adversary.py
adlib/adversaries/binary_greedy.py
adlib/adversaries/coordinate_greedy.py
adlib/adversaries/cost_sensitive.py
adlib/adversaries/feature_deletion.py
adlib/adversaries/free_range_attack.py
adlib/adversaries/good_word.py
adlib/adversaries/gradient_descent.py
adlib/adversaries/k_insertion.py
adlib/adversaries/label_flipping.py
adlib/adversaries/restrained_attack.py
adlib/adversaries/simple_gradient_descent.py
adlib/adversaries/simple_optimize.py
adlib/adversaries/datamodification/__init__.py
adlib/adversaries/datamodification/data_modification.py
adlib/adversaries/datatransform/__init__.py
adlib/adversaries/datatransform/data_transform.py
adlib/learners/__init__.py
adlib/learners/adversary_aware.py
adlib/learners/alternating_trim_learner.py
adlib/learners/feature_deletion.py
adlib/learners/iterative_retraining_learner.py
adlib/learners/l_infinity_svm.py
adlib/learners/learner.py
adlib/learners/outlier_removal_learner.py
adlib/learners/retraining.py
adlib/learners/simple_learner.py
adlib/learners/svm_freerange.py
adlib/learners/svm_restrained.py
adlib/learners/trim_learner.py
adlib/learners/models/__init__.py
adlib/learners/models/model.py
adlib/learners/models/sklearner.py
adlib/tests/__init__.py
adlib/tests/adversaries/__init__.py
adlib/tests/adversaries/adversarial_learning_test.py
adlib/tests/adversaries/binary_greedy_400.py
adlib/tests/adversaries/binary_greedy_test.py
adlib/tests/adversaries/coordinate_greedy_400.py
adlib/tests/adversaries/cost_sensitive_test.py
adlib/tests/adversaries/data_modification_test.py
adlib/tests/adversaries/data_transform_test.py
adlib/tests/adversaries/feature_deletion_400.py
adlib/tests/adversaries/feature_deletion_test.py
adlib/tests/adversaries/free_range_400.py
adlib/tests/adversaries/free_range_test.py
adlib/tests/adversaries/good_word_400.py
adlib-1.2.1.dist-info/METADATA
adlib-1.2.1.dist-info/RECORD
adlib-1.2.1.dist-info/WHEEL
adlib-1.2.1.dist-info/top_level.txt
